vortex/__init__.py
vortex/boot.py
vortex/cli.py
vortex/control.py
vortex/euclid.py
vortex/gui.py
vortex/pattern.py
vortex/repl.py
vortex/stream.py
vortex/utils.py
vortex/vortex.py
tidalvortex-0.1.0a0.dist-info/entry_points.txt
tidalvortex-0.1.0a0.dist-info/LICENSE
tidalvortex-0.1.0a0.dist-info/WHEEL
tidalvortex-0.1.0a0.dist-info/METADATA
tidalvortex-0.1.0a0.dist-info/RECORD
