Metadata-Version: 2.1
Name: tidalvortex
Version: 0.1.0a0
Summary: Python port of TidalCycles
Home-page: https://github.com/tidalcycles/vortex
License: GPL-3.0-or-later
Author: Tidal Cyclists
Author-email: vortex@tidalcycles.org
Requires-Python: >=3.8,<3.11
Classifier: License :: OSI Approved :: GNU General Public License v3 or later (GPLv3+)
Classifier: Programming Language :: Python :: 3
Classifier: Programming Language :: Python :: 3.10
Classifier: Programming Language :: Python :: 3.8
Classifier: Programming Language :: Python :: 3.9
Requires-Dist: LinkPython (>=0.1.1,<0.2.0)
Requires-Dist: PyQt5 (>=5.15.7,<6.0.0)
Requires-Dist: QScintilla (>=2.13.3,<3.0.0)
Requires-Dist: ipython (>=8.4.0,<9.0.0)
Requires-Dist: parsy (>=1.4.0,<2.0.0)
Requires-Dist: pyliblo3 (>=0.13.0,<0.14.0)
Project-URL: Repository, https://github.com/tidalcycles/vortex
